py_openai_assistant/Assistant.py
py_openai_assistant/FileManager.py
py_openai_assistant/__init__.py
py_openai_assistant-0.1.4.dist-info/METADATA
py_openai_assistant-0.1.4.dist-info/WHEEL
py_openai_assistant-0.1.4.dist-info/RECORD
