Metadata-Version: 2.1
Name: py_openai_assistant
Version: 0.1.4
Summary: 
Author: BenderScript
Author-email: 6779302+BenderScript@users.noreply.github.com
Requires-Python: >=3.11,<4.0
Classifier: Programming Language :: Python :: 3
Classifier: Programming Language :: Python :: 3.11
Classifier: Programming Language :: Python :: 3.12
Requires-Dist: colorama (>=0.4.6,<0.5.0)
Requires-Dist: openai (>=1.8.0,<2.0.0)
Requires-Dist: python-dotenv (>=1.0.0,<2.0.0)
